django_from_excel/__init__.py
django_from_excel/management/__init__.py
django_from_excel/management/commands/__init__.py
django_from_excel/management/commands/buildfrom.py
django_from_excel-0.1.2.dist-info/LICENSE
django_from_excel-0.1.2.dist-info/WHEEL
django_from_excel-0.1.2.dist-info/METADATA
django_from_excel-0.1.2.dist-info/RECORD
