Metadata-Version: 2.1
Name: django-from-excel
Version: 0.1.2
Summary: Automatically build Django models from an Excel file
Home-page: https://github.com/johncmacy/django-from-excel
License: MIT
Keywords: excel,convert,spreadsheet,django,model
Author: John Macy
Author-email: johncmacy@gmail.com
Requires-Python: >=3.9,<4.0
Classifier: License :: OSI Approved :: MIT License
Classifier: Programming Language :: Python :: 3
Classifier: Programming Language :: Python :: 3.9
Requires-Dist: Django (>=3.2.7,<4.0.0)
Requires-Dist: openpyxl (>=3.0.8,<4.0.0)
Requires-Dist: pandas (>=1.3.3,<2.0.0)
Project-URL: Repository, https://github.com/johncmacy/django-from-excel
